{
  "excellent": "Great!",
  "allQuestionsAnswered": "You answered all the questions",
  "totalQuestions": "Total questions",
  "rightAnswers": "Right answers",
  "wrongAnswers": "Wrong answers",
  "totalTime": "Time",
  "startAgain": "Start again",
  "goToMenu": "Back to menu",
  "checkAnswers": "Check Answers",
  "addToFavourites": "Agregar a los favoritos ⭐",
  "removeFromFavourites": "Quitar de favoritos ⭐",
  "examSuccess": "Exam passed",
  "examSuccessDescription": "Excellent result! Congratulations!",
  "examNotSuccess": "Exam not passed",
  "examNotSuccessDescription": "Learn your mistakes and try again"
}